instrumentman/__init__.py
instrumentman/__main__.py
instrumentman/_version.py
instrumentman/calculations.py
instrumentman/py.typed
instrumentman/schema_targets.json
instrumentman/targets.py
instrumentman/utils.py
instrumentman/control/__init__.py
instrumentman/control/app.py
instrumentman/datatransfer/__init__.py
instrumentman/datatransfer/app.py
instrumentman/filetransfer/__init__.py
instrumentman/filetransfer/app.py
instrumentman/inclination/__init__.py
instrumentman/inclination/app.py
instrumentman/jobs/__init__.py
instrumentman/jobs/app.py
instrumentman/morse/__init__.py
instrumentman/morse/app.py
instrumentman/panorama/__init__.py
instrumentman/panorama/measure.py
instrumentman/panorama/metadata.py
instrumentman/panorama/process.py
instrumentman/panorama/schema_metadata.json
instrumentman/protocoltest/__init__.py
instrumentman/protocoltest/app.py
instrumentman/setmeasurement/__init__.py
instrumentman/setmeasurement/measure.py
instrumentman/setmeasurement/process.py
instrumentman/setmeasurement/schema_session.json
instrumentman/setmeasurement/sessions.py
instrumentman/settings/__init__.py
instrumentman/settings/io.py
instrumentman/settings/load.py
instrumentman/settings/save.py
instrumentman/settings/schema_settings.json
instrumentman/settings/validate.py
instrumentman/setup/__init__.py
instrumentman/setup/app.py
instrumentman/setup/convert.py
instrumentman/station/__init__.py
instrumentman/station/calculate.py
instrumentman/station/upload.py
instrumentman/terminal/__init__.py
instrumentman/terminal/app.py
instrumentman/terminal/app.tcss
instrumentman-0.5.0.dist-info/METADATA
instrumentman-0.5.0.dist-info/WHEEL
instrumentman-0.5.0.dist-info/entry_points.txt
instrumentman-0.5.0.dist-info/licenses/LICENSE
instrumentman-0.5.0.dist-info/RECORD
