Metadata-Version: 2.4
Name: instrumentman
Version: 0.5.0
Summary: Surveying instrument automation applications.
Project-URL: Documentation, https://instrumentman.readthedocs.io
Project-URL: Repository, https://github.com/MrClock8163/Instrumentman
Project-URL: Issues, https://github.com/MrClock8163/Instrumentman/issues
Project-URL: Changelog, https://instrumentman.readthedocs.io/latest/changelog
Author-email: MrClock <mrclock8163@gmail.com>
License-Expression: MIT
License-File: LICENSE
Keywords: automation,geocom,gsi,leica,monitoring,surveying,totalstation
Classifier: Development Status :: 4 - Beta
Classifier: Intended Audience :: Developers
Classifier: Intended Audience :: Science/Research
Classifier: License :: OSI Approved :: MIT License
Classifier: Operating System :: OS Independent
Classifier: Programming Language :: Python
Classifier: Programming Language :: Python :: 3
Classifier: Programming Language :: Python :: 3.11
Classifier: Programming Language :: Python :: 3.12
Classifier: Programming Language :: Python :: 3.13
Classifier: Programming Language :: Python :: 3.14
Classifier: Topic :: Education
Classifier: Topic :: Scientific/Engineering
Classifier: Topic :: Scientific/Engineering :: GIS
Classifier: Topic :: Software Development
Classifier: Topic :: Software Development :: Libraries
Classifier: Topic :: Software Development :: Libraries :: Python Modules
Classifier: Topic :: Terminals :: Serial
Classifier: Typing :: Typed
Requires-Python: >=3.11
Requires-Dist: click-extra~=5.0.2
Requires-Dist: cloup~=3.0.7
Requires-Dist: geocompy~=0.14.0
Requires-Dist: jmespath~=1.0.1
Requires-Dist: jsonschema~=4.21
Requires-Dist: numpy~=2.0
Requires-Dist: pillow~=11.0
Requires-Dist: pyserial~=3.5.0
Requires-Dist: pyyaml~=6.0.2
Requires-Dist: rapidfuzz~=3.13.0
Requires-Dist: rich>=13.9
Requires-Dist: textual>=3.2.0
Requires-Dist: toml~=0.10.2
Provides-Extra: all
Requires-Dist: opencv-python~=4.8; extra == 'all'
Provides-Extra: panorama
Requires-Dist: opencv-python~=4.8; extra == 'panorama'
